yrt_7895pckge/__init__.py
yrt_7895pckge/module.py
yrt_7895pckge/data/Users.csv
yrt_7895pckge-0.1.dist-info/METADATA
yrt_7895pckge-0.1.dist-info/WHEEL
yrt_7895pckge-0.1.dist-info/entry_points.txt
yrt_7895pckge-0.1.dist-info/top_level.txt
yrt_7895pckge-0.1.dist-info/RECORD
